qscaler/__init__.py
qscaler/brokers/__init__.py
qscaler/brokers/broker.py
qscaler/brokers/brokers_factory.py
qscaler/brokers/redis_broker.py
qscaler/configuration/__init__.py
qscaler/configuration/config.py
qscaler/event_loop/__init__.py
qscaler/event_loop/event_loop.py
qscaler/k8s/__init__.py
qscaler/k8s/k8s_client.py
qscaler/models/__init__.py
qscaler/models/qworker.py
qscaler/models/scaler_config.py
qscaler/utils/__init__.py
qscaler/utils/singleton.py
qscaler/worker.py
qscaler-0.0.1.dist-info/LICENSE
qscaler-0.0.1.dist-info/METADATA
qscaler-0.0.1.dist-info/WHEEL
qscaler-0.0.1.dist-info/RECORD
