Metadata-Version: 2.3
Name: qscaler
Version: 0.0.1
Summary: Python SDK for QScaler - Kubernetes-native queue worker autoscaler
Author: Quickube
Requires-Python: >=3.11,<4.0
Classifier: Programming Language :: Python :: 3
Classifier: Programming Language :: Python :: 3.11
Classifier: Programming Language :: Python :: 3.12
Classifier: Programming Language :: Python :: 3.13
Requires-Dist: kubernetes (>=31.0.0,<32.0.0)
Requires-Dist: pydantic (>=2.10.4,<3.0.0)
Requires-Dist: redis
